[
	{
		"inputs": [
			{
				"internalType": "string",
				"name": "name_",
				"type": "string"
			},
			{
				"internalType": "string",
				"name": "symbol_",
				"type": "string"
			},
			{
				"internalType": "address[]",
				"name": "tokenAddresses_",
				"type": "address[]"
			},
			{
				"internalType": "uint256[]",
				"name": "percentageHoldings_",
				"type": "uint256[]"
			},
			{
				"internalType": "address",
				"name": "owner_",
				"type": "address"
			},
			{
				"internalType": "uint256",
				"name": "ownerFee_",
				"type": "uint256"
			}
		],
		"stateMutability": "nonpayable",
		"type": "constructor"
	},
	{
		"anonymous": false,
		"inputs": [
			{
				"indexed": true,
				"internalType": "address",
				"name": "owner",
				"type": "address"
			},
			{
				"indexed": true,
				"internalType": "address",
				"name": "spender",
				"type": "address"
			},
			{
				"indexed": false,
				"internalType": "uint256",
				"name": "value",
				"type": "uint256"
			}
		],
		"name": "Approval",
		"type": "event"
	},
	{
		"anonymous": false,
		"inputs": [
			{
				"indexed": true,
				"internalType": "address",
				"name": "_from",
				"type": "address"
			},
			{
				"indexed": false,
				"internalType": "uint256",
				"name": "_depositAmount",
				"type": "uint256"
			},
			{
				"indexed": false,
				"internalType": "uint256",
				"name": "_priorValueLocked",
				"type": "uint256"
			},
			{
				"indexed": false,
				"internalType": "uint256",
				"name": "_tokensMinted",
				"type": "uint256"
			}
		],
		"name": "Buy",
		"type": "event"
	},
	{
		"anonymous": false,
		"inputs": [
			{
				"indexed": true,
				"internalType": "address",
				"name": "_from",
				"type": "address"
			},
			{
				"indexed": false,
				"internalType": "uint256",
				"name": "_tokensBurned",
				"type": "uint256"
			}
		],
		"name": "RedeemAssets",
		"type": "event"
	},
	{
		"anonymous": false,
		"inputs": [
			{
				"indexed": true,
				"internalType": "address",
				"name": "_from",
				"type": "address"
			},
			{
				"indexed": false,
				"internalType": "uint256",
				"name": "_tokensBurned",
				"type": "uint256"
			},
			{
				"indexed": false,
				"internalType": "uint256",
				"name": "returnedEth",
				"type": "uint256"
			}
		],
		"name": "SellAssets",
		"type": "event"
	},
	{
		"anonymous": false,
		"inputs": [
			{
				"indexed": true,
				"internalType": "address",
				"name": "from",
				"type": "address"
			},
			{
				"indexed": true,
				"internalType": "address",
				"name": "to",
				"type": "address"
			},
			{
				"indexed": false,
				"internalType": "uint256",
				"name": "value",
				"type": "uint256"
			}
		],
		"name": "Transfer",
		"type": "event"
	},
	{
		"inputs": [
			{
				"internalType": "address",
				"name": "owner",
				"type": "address"
			},
			{
				"internalType": "address",
				"name": "spender",
				"type": "address"
			}
		],
		"name": "allowance",
		"outputs": [
			{
				"internalType": "uint256",
				"name": "",
				"type": "uint256"
			}
		],
		"stateMutability": "view",
		"type": "function"
	},
	{
		"inputs": [
			{
				"internalType": "address",
				"name": "spender",
				"type": "address"
			},
			{
				"internalType": "uint256",
				"name": "amount",
				"type": "uint256"
			}
		],
		"name": "approve",
		"outputs": [
			{
				"internalType": "bool",
				"name": "",
				"type": "bool"
			}
		],
		"stateMutability": "nonpayable",
		"type": "function"
	},
	{
		"inputs": [
			{
				"internalType": "address",
				"name": "",
				"type": "address"
			}
		],
		"name": "assetQuantities",
		"outputs": [
			{
				"internalType": "uint256",
				"name": "",
				"type": "uint256"
			}
		],
		"stateMutability": "view",
		"type": "function"
	},
	{
		"inputs": [
			{
				"internalType": "address",
				"name": "account",
				"type": "address"
			}
		],
		"name": "balanceOf",
		"outputs": [
			{
				"internalType": "uint256",
				"name": "",
				"type": "uint256"
			}
		],
		"stateMutability": "view",
		"type": "function"
	},
	{
		"inputs": [],
		"name": "buy",
		"outputs": [],
		"stateMutability": "payable",
		"type": "function"
	},
	{
		"inputs": [],
		"name": "decimals",
		"outputs": [
			{
				"internalType": "uint8",
				"name": "",
				"type": "uint8"
			}
		],
		"stateMutability": "view",
		"type": "function"
	},
	{
		"inputs": [
			{
				"internalType": "address",
				"name": "spender",
				"type": "address"
			},
			{
				"internalType": "uint256",
				"name": "subtractedValue",
				"type": "uint256"
			}
		],
		"name": "decreaseAllowance",
		"outputs": [
			{
				"internalType": "bool",
				"name": "",
				"type": "bool"
			}
		],
		"stateMutability": "nonpayable",
		"type": "function"
	},
	{
		"inputs": [
			{
				"internalType": "address",
				"name": "spender",
				"type": "address"
			},
			{
				"internalType": "uint256",
				"name": "addedValue",
				"type": "uint256"
			}
		],
		"name": "increaseAllowance",
		"outputs": [
			{
				"internalType": "bool",
				"name": "",
				"type": "bool"
			}
		],
		"stateMutability": "nonpayable",
		"type": "function"
	},
	{
		"inputs": [],
		"name": "initialisePortfolio",
		"outputs": [],
		"stateMutability": "payable",
		"type": "function"
	},
	{
		"inputs": [],
		"name": "name",
		"outputs": [
			{
				"internalType": "string",
				"name": "",
				"type": "string"
			}
		],
		"stateMutability": "view",
		"type": "function"
	},
	{
		"inputs": [],
		"name": "owner",
		"outputs": [
			{
				"internalType": "address",
				"name": "",
				"type": "address"
			}
		],
		"stateMutability": "view",
		"type": "function"
	},
	{
		"inputs": [],
		"name": "ownerFee",
		"outputs": [
			{
				"internalType": "uint256",
				"name": "",
				"type": "uint256"
			}
		],
		"stateMutability": "view",
		"type": "function"
	},
	{
		"inputs": [
			{
				"internalType": "uint256",
				"name": "",
				"type": "uint256"
			}
		],
		"name": "percentageHoldings",
		"outputs": [
			{
				"internalType": "uint256",
				"name": "",
				"type": "uint256"
			}
		],
		"stateMutability": "view",
		"type": "function"
	},
	{
		"inputs": [
			{
				"internalType": "uint256",
				"name": "tokensToSell",
				"type": "uint256"
			}
		],
		"name": "redeemAssets",
		"outputs": [],
		"stateMutability": "nonpayable",
		"type": "function"
	},
	{
		"inputs": [
			{
				"internalType": "uint256",
				"name": "tokensToSell",
				"type": "uint256"
			}
		],
		"name": "sellAssets",
		"outputs": [],
		"stateMutability": "nonpayable",
		"type": "function"
	},
	{
		"inputs": [],
		"name": "symbol",
		"outputs": [
			{
				"internalType": "string",
				"name": "",
				"type": "string"
			}
		],
		"stateMutability": "view",
		"type": "function"
	},
	{
		"inputs": [
			{
				"internalType": "uint256",
				"name": "",
				"type": "uint256"
			}
		],
		"name": "tokenAddresses",
		"outputs": [
			{
				"internalType": "address",
				"name": "",
				"type": "address"
			}
		],
		"stateMutability": "view",
		"type": "function"
	},
	{
		"inputs": [],
		"name": "totalSupply",
		"outputs": [
			{
				"internalType": "uint256",
				"name": "",
				"type": "uint256"
			}
		],
		"stateMutability": "view",
		"type": "function"
	},
	{
		"inputs": [
			{
				"internalType": "address",
				"name": "to",
				"type": "address"
			},
			{
				"internalType": "uint256",
				"name": "amount",
				"type": "uint256"
			}
		],
		"name": "transfer",
		"outputs": [
			{
				"internalType": "bool",
				"name": "",
				"type": "bool"
			}
		],
		"stateMutability": "nonpayable",
		"type": "function"
	},
	{
		"inputs": [
			{
				"internalType": "address",
				"name": "from",
				"type": "address"
			},
			{
				"internalType": "address",
				"name": "to",
				"type": "address"
			},
			{
				"internalType": "uint256",
				"name": "amount",
				"type": "uint256"
			}
		],
		"name": "transferFrom",
		"outputs": [
			{
				"internalType": "bool",
				"name": "",
				"type": "bool"
			}
		],
		"stateMutability": "nonpayable",
		"type": "function"
	},
	{
		"stateMutability": "payable",
		"type": "receive"
	}
]
